{"overview": "Ozark Concierge Clinic provides membership-based concierge primary care with direct physician access in Rogers, AR. The practice offers weight loss management, hormonal balance, and aesthetic treatments, prioritizing personalized, proactive healthcare.", "highlights": ["Direct physician access", "Weight loss management", "Hormonal balance and aesthetic services"], "services": [], "consultModel": "", "targetAudience": "Individuals in Northwest Arkansas seeking preventative, personalized healthcare with direct physician access."}