{"overview": "EHormones MD provides testosterone replacement therapy, hormone replacement therapy, and age-management treatments that are medically supervised and tailored to individual needs. With dozens of locations across the United States, they serve men seeking to address hormonal imbalances and age-related changes.", "highlights": ["Available in 30+ states", "Bioidentical hormone therapy", "Free 24/7 consultations"], "services": ["TRT", "HRT", "BHRT", "Wellness"], "consultModel": "in-person", "targetAudience": "Men aged 30 and older experiencing low testosterone or other age-related hormonal imbalances."}