{"overview": "Hormones by Design specializes in helping women in perimenopause and menopause regain balance and energy through personalized injectable hormone therapy with dedicated providers across six Texas locations.", "highlights": ["Injectable BHRT with monthly adjustments based on labs and patient response", "Consistent, dedicated providers throughout treatment", "Thyroid balancing"], "services": ["HRT", "BHRT", "Pellets"], "consultModel": "hybrid", "targetAudience": "Women in perimenopause and menopause seeking personalized hormone care with a provider who stays with them through treatment."}