{"overview": "Optimal Hormones & Wellness offers hormone therapy, weight management, dermatology, and addiction recovery services. Care is delivered through a comprehensive, data-driven approach that examines hormones, weight, sleep, stress, labs, and lifestyle together.", "highlights": ["Bio-identical hormone replacement and cortisol optimization", "Precision diagnostics for hormones, metabolism, nutrition, and thyroid", "MAT program for addiction recovery"], "services": ["TRT", "HRT", "Wellness"], "consultModel": "", "targetAudience": "People who feel stuck after trying various treatments and want a comprehensive, personalized approach to hormone balance and wellness."}