{"overview": "A urology practice providing advanced treatments for men's health conditions. Board-certified specialists serve busy professionals throughout Middle Tennessee with personalized care.", "highlights": ["Board-certified urology specialists in men's health", "Multiple office locations throughout Middle Tennessee", "Treats Low T, ED, BPH, male infertility, and Peyronie's disease"], "services": ["TRT"], "consultModel": "in-person", "targetAudience": "Busy professionals seeking specialized men's health urology treatment."}