{"overview": "Idaho Health and Hormones provides hormone optimization and advanced therapies to restore energy and optimize performance. Care is personalized and data-driven, using cutting-edge technologies not available at traditional clinics.", "highlights": ["Idaho's only academic wellness center", "Cutting-edge non-invasive therapies including EMFACE, Emsculpt NEO, EXOMIND, and Core to Floor", "Data-driven diagnostics and personalized treatment protocols"], "services": ["HRT", "Wellness"], "consultModel": "", "targetAudience": "Patients seeking hormone therapy and advanced wellness treatments for energy, metabolism, strength, mental clarity, and sexual health."}