{"overview": "Elite Hormones provides personalized hormone replacement therapy for men and women with locations in Madison, Wausau, and Eau Claire, Wisconsin. The clinic treats hormonal imbalances including menopause, andropause, and sexual dysfunction.", "highlights": ["Medical weight loss program", "Sexual dysfunction treatment", "Athletic and growth hormone optimization"], "services": ["TRT", "HRT", "Wellness"], "consultModel": "", "targetAudience": "Men and women in Wisconsin with hormonal imbalances seeking hormone therapy, weight loss support, or anti-aging treatments."}