{"overview": "Mid-Florida Age Management is an age management wellness clinic in Ocala led by board-certified physician Dr. Gene Turner. The clinic delivers personalized care addressing root causes of aging to help clients maintain vitality and function.", "highlights": ["Physician-led care (Dr. Turner on-site daily)", "Hormone pellet therapy and HRT", "Aesthetic treatments including body sculpting and facial rejuvenation"], "services": ["HRT", "BHRT", "Pellets", "Wellness"], "consultModel": "in-person", "targetAudience": "Active adults seeking age management services to maintain vitality, appearance, and quality of life as they age."}