{"overview": "Montana Aging Gracefully is a longevity-focused clinic integrating hormone replacement therapy, aesthetic treatments, and comprehensive wellness services. The clinic develops personalized anti-aging treatment plans combining medical therapies with support for the four pillars of health: diet, exercise, sleep, and stress reduction.", "highlights": ["Personalized longevity plans", "Bioidentical hormone pellets and injectables", "In-house lab services and body composition analysis"], "services": ["HRT", "GLP-1", "Wellness", "Pellets"], "consultModel": "in-person", "targetAudience": "For individuals of any age interested in longevity medicine and anti-aging care."}