{"overview": "PURE Regenerative Medicine is a physician-led aesthetics and regenerative medicine clinic. Services include aesthetic treatments, bioidentical hormone therapy, and medical weight loss programs delivered through personalized, physician-administered care.", "highlights": ["Physician-administered treatments", "Bioidentical hormone replacement therapy", "Medically supervised weight loss programs"], "services": ["BHRT", "Wellness"], "consultModel": "", "targetAudience": "People seeking preventive wellness care, aesthetic treatments, and regenerative medicine."}