{"overview": "Renew Vitality provides personalized testosterone replacement therapy and hormone management for men. The clinic operates nationwide locations with a care model that includes physician consultation and home delivery of customized treatment.", "highlights": ["Multiple nationwide clinic locations", "Concierge patient support", "Performance supplements"], "services": ["TRT", "HRT", "GLP-1", "Wellness"], "consultModel": "", "targetAudience": "Men with low testosterone symptoms or seeking hormone optimization and age management."}