{"overview": "Man Up provides physician-monitored hormone optimization therapy for men and women. Treatment includes routine blood work and personalized dosing adjustments to achieve optimal hormone levels.", "highlights": ["Specialty physician-monitored treatment", "Routine blood work and dosage adjustments", "Hormone therapy for men and women"], "services": ["TRT", "HRT"], "consultModel": "", "targetAudience": "Men and women experiencing hormone imbalances who want to optimize hormone levels through physician-supervised therapy."}